{"questions":[{"question":"Software engineering refers to:","answers":["Only writing code","Software tests","The whole life cycle of software","Software design"],"correct_ans":"3","level":"1","team":"Panther"},{"question":"In AGILE programming:","answers":["Perform tests in every end of iteration","There is no separate phase for tests","Giving to customer examine the software before every iteration","Giving to customer examine the software after every iteration"],"correct_ans":"2","level":"2","team":"Panther"},{"question":"can Singelton establish and restore more than one object ?","answers":["can return only one object, it's the whole idea","No, it does not establish objects, just checking their existence","Yes, you can specify that it will return a predetermined amount of objects","No, it does not return objects, only answers if they exist"],"correct_ans":"3","level":"3","team":"Panther"},{"question":"what is SaaS Advantages Over The Traditional Software Model ?","answers":["The Saas  model significantly reduces  the expenses typically  associated with locally hosted  software applications","The SaaS model is not reduces  the expenses typically  associated with locally hosted  software applications","In SaaS A separate license must be purchased for each workstation that will access  an enterprise software application","Non of the above"],"correct_ans":"1","level":"2","team":"Panther"},{"question":"What does MVC model contain ?","answers":["View - Controller \u2013 Model","Controller - View \u2013 Model","Controller - Model - View ","None of the above"],"correct_ans":"1","level":"1","team":"Panther"},{"question":"Which of the following is true about Factory method ?","answers":["Convert the interface of a class into another interface clients expect. ","define an interface for creating an object, but let classes decide which class to instantiate.","Allow an object to alter its behavior when its internal state changes.","Provide a surrogate or place holder for another object to control access to it."],"correct_ans":"2","level":"2","team":"Panther"},{"question":"Which of the?","answers":["Convert the interface of a class into another interface clients expect. ","Convert the interface of a class into another interface clients expect. ","Convert the interface of a class into another interface clients expect. ","Convert the interface of a class into another interface clients expect. "],"correct_ans":"1","level":"3","team":"Panther"},{"question":"Which of the following is true about Factory method ?","answers":["Convert the interface of a class into another interface clients expect. ","Convert the interface of a class into another interface clients expect. ","Convert the interface of a class into another interface clients expect. ","Convert the interface of a class into another interface clients expect. "],"correct_ans":"1","level":"1","team":"Panther"},{"question":"Which of the following is true about Factory method ?","answers":["Convert the interface of a class into another interface clients expect. ","Convert the interface of a class into another interface clients expect. ","Convert the interface of a class into another interface clients expect. ","Convert the interface of a class into another interface clients expect. "],"correct_ans":"1","level":"1","team":"Panther"},{"question":"Which of the following is true about Factory method ?","answers":["Convert the interface of a class into another interface clients expect. ","Convert the interface of a class into another interface clients expect. ","Convert the interface of a class into another interface clients expect. ","Convert the interface of a class into another interface clients expect. "],"correct_ans":"1","level":"1","team":"Panther"},{"question":"Which of the following is true about Factory method ?","answers":["Convert the interface of a class into another interface clients expect. ","Convert the interface of a class into another interface clients expect. ","Convert the interface of a class into another interface clients expect. ","Convert the interface of a class into another interface clients expect. "],"correct_ans":"1","level":"1","team":"Panther"},{"question":"Which of the following is true about Factory method ?","answers":["Convert the interface of a class into another interface clients expect. ","Convert the interface of a class into another interface clients expect. ","Convert the interface of a class into another interface clients expect. ","Convert the interface of a class into another interface clients expect. "],"correct_ans":"1","level":"1","team":"Panther"},{"question":"Which of the following is true about Factory method ?","answers":["Convert the interface of a class into another interface clients expect. ","Convert the interface of a class into another interface clients expect. ","Convert the interface of a class into another interface clients expect. ","Convert the interface of a class into another interface clients expect. "],"correct_ans":"1","level":"1","team":"Panther"},{"question":"Which of the following is true about Factory method ?","answers":["Convert the interface of a class into another interface clients expect. ","Convert the interface of a class into another interface clients expect. ","Convert the interface of a class into another interface clients expect. ","Convert the interface of a class into another interface clients expect. "],"correct_ans":"1","level":"1","team":"Panther"},{"question":"Which of the following is true about Factory method ?","answers":["Convert the interface of a class into another interface clients expect. ","Convert the interface of a class into another interface clients expect. ","Convert the interface of a class into another interface clients expect. ","Convert the interface of a class into another interface clients expect. "],"correct_ans":"1","level":"1","team":"Panther"},{"question":"Which of the following is true about Factory method ?","answers":["Convert the interface of a class into another interface clients expect. ","Convert the interface of a class into another interface clients expect. ","Convert the interface of a class into another interface clients expect. ","Convert the interface of a class into another interface clients expect. "],"correct_ans":"1","level":"1","team":"Panther"},{"question":"Which of the following is true about Factory method ?","answers":["Convert the interface of a class into another interface clients expect. ","Convert the interface of a class into another interface clients expect. ","Convert the interface of a class into another interface clients expect. ","Convert the interface of a class into another interface clients expect. "],"correct_ans":"1","level":"1","team":"Panther"},{"question":"Which of the following is true about Factory method ?","answers":["Convert the interface of a class into another interface clients expect. ","Convert the interface of a class into another interface clients expect. ","Convert the interface of a class into another interface clients expect. ","Convert the interface of a class into another interface clients expect. "],"correct_ans":"1","level":"1","team":"Panther"},{"question":"Which of the following is true about Factory method ?","answers":["Convert the interface of a class into another interface clients expect. ","Convert the interface of a class into another interface clients expect. ","Convert the interface of a class into another interface clients expect. ","Convert the interface of a class into another interface clients expect. "],"correct_ans":"1","level":"1","team":"Panther"},{"question":"Which of the following is true about Factory method ?","answers":["Convert the interface of a class into another interface clients expect. ","Convert the interface of a class into another interface clients expect. ","Convert the interface of a class into another interface clients expect. ","Convert the interface of a class into another interface clients expect. "],"correct_ans":"1","level":"1","team":"Panther"},{"question":"Which of the following is true about Factory method ?","answers":["Convert the interface of a class into another interface clients expect. ","Convert the interface of a class into another interface clients expect. ","Convert the interface of a class into another interface clients expect. ","Convert the interface of a class into another interface clients expect. "],"correct_ans":"1","level":"1","team":"Panther"}]}